pwm_lightness.py
pwm_lightness-1.0.1.dist-info/LICENSE
pwm_lightness-1.0.1.dist-info/METADATA
pwm_lightness-1.0.1.dist-info/WHEEL
pwm_lightness-1.0.1.dist-info/top_level.txt
pwm_lightness-1.0.1.dist-info/RECORD
