Metadata-Version: 2.1
Name: pwm-lightness
Version: 1.0.1
Summary: A tiny library to calculate CIE 1931 lightness tables for eyeball friendly PWM LED brightness.
Home-page: https://github.com/gpshead/pwm_lightness
Author: Gregory P. Smith
Author-email: greg@krypto.org
License: Apache 2.0
Platform: UNKNOWN
Classifier: Development Status :: 4 - Beta
Classifier: Intended Audience :: Developers
Classifier: Intended Audience :: Education
Classifier: License :: OSI Approved :: Apache Software License
Classifier: Programming Language :: Python :: 3
Classifier: Programming Language :: Python :: Implementation :: CPython
Classifier: Programming Language :: Python :: Implementation :: PyPy
Classifier: Programming Language :: Python :: Implementation :: MicroPython
Requires-Python: >=3.6
